empiar/EMPIAR_logo.png
empiar/__init__.py
empiar/bibtex.py
empiar/constants.py
empiar/protocols.conf
empiar/utils.py
empiar/protocols/__init__.py
empiar/protocols/protocol_downloader.py
empiar/protocols/protocol_empiar_submission.py
empiar/templates/empiar_deposition_template.json
scipion_em_empiar-3.1.1.dist-info/LICENSE
scipion_em_empiar-3.1.1.dist-info/METADATA
scipion_em_empiar-3.1.1.dist-info/WHEEL
scipion_em_empiar-3.1.1.dist-info/entry_points.txt
scipion_em_empiar-3.1.1.dist-info/top_level.txt
scipion_em_empiar-3.1.1.dist-info/RECORD
