Metadata-Version: 2.1
Name: scipion-em-empiar
Version: 3.1.1
Summary: A Scipion plugin to make depositions to EMPIAR
Home-page: https://github.com/scipion-em/scipion-em-empiar
Author: I2PC
Author-email: scipion@cnb.csic.es
License: UNKNOWN
Project-URL: Bug Reports, https://github.com/scipion-em/scipion-em-empiar/issues
Project-URL: Source, https://github.com/scipion-em/scipion-em-empiar/
Keywords: scipion empiar scipion-3.0
Platform: UNKNOWN
Classifier: Development Status :: 5 - Production/Stable
Classifier: License :: OSI Approved :: GNU General Public License v3 (GPLv3)
Classifier: Programming Language :: Python :: 3
Requires-Dist: empiar-depositor
Requires-Dist: jsonschema
Requires-Dist: scipion-em
